mregancs501a10py/CS501_Assignment10.py
mregancs501a10py/__init__.py
mregancs501a10py-0.0.1.dist-info/LICENSE
mregancs501a10py-0.0.1.dist-info/METADATA
mregancs501a10py-0.0.1.dist-info/WHEEL
mregancs501a10py-0.0.1.dist-info/top_level.txt
mregancs501a10py-0.0.1.dist-info/RECORD
